{
    "keep": {
        "days": true,
        "amount": 7
    },
    "auditLog": "C:\\Users\\temiloluwao\\Downloads\\TheBanckendFiles\\server\\logs\\.4fb3febe09fbee6cda7e9924a01540edc8c9e70c-audit.json",
    "files": [
        {
            "date": 1770365559997,
            "name": "C:\\Users\\temiloluwao\\Downloads\\TheBanckendFiles\\server\\logs\\http-2026-02-06.log",
            "hash": "f2e51b131e73599c8eb4872e0ea90889b7b1db504b46d64c86107a98ff7b4b99"
        },
        {
            "date": 1770589975380,
            "name": "C:\\Users\\temiloluwao\\Downloads\\TheBanckendFiles\\server\\logs\\http-2026-02-08.log",
            "hash": "4e0a5e31a2cd715f71cb7e047a6dc4b6b476bc0b72b998febd467f219559a322"
        },
        {
            "date": 1770591779358,
            "name": "C:\\Users\\temiloluwao\\Downloads\\TheBanckendFiles\\server\\logs\\http-2026-02-09.log",
            "hash": "a9cbd7e12617d9673825d52d9991499a2ae9c5bfffc298452d469954a995198b"
        }
    ],
    "hashType": "sha256"
}