{
    "keep": {
        "days": true,
        "amount": 7
    },
    "auditLog": "C:\\Users\\VINCENT\\Desktop\\Temiloluwa\\TheBanckendFiles\\server\\logs\\.d60cc5e4b0a4d413b21760b0d0ee5c54803400a2-audit.json",
    "files": [
        {
            "date": 1776408970884,
            "name": "C:\\Users\\VINCENT\\Desktop\\Temiloluwa\\TheBanckendFiles\\server\\logs\\http-2026-04-17.log",
            "hash": "f65e84bb035c3fa8dd9e6c54c19122e7263fb3e612a2aa2b721ee65fa5eeed37"
        },
        {
            "date": 1776516586612,
            "name": "C:\\Users\\VINCENT\\Desktop\\Temiloluwa\\TheBanckendFiles\\server\\logs\\http-2026-04-18.log",
            "hash": "c295f73e51dac5bcc1758c44a7120bcff77114ac8925d596222beb5f35f2af85"
        },
        {
            "date": 1776619333797,
            "name": "C:\\Users\\VINCENT\\Desktop\\Temiloluwa\\TheBanckendFiles\\server\\logs\\http-2026-04-19.log",
            "hash": "a161d57c00c2b669665aa405e11cb685784b7ee281cfc665829f37eb00725671"
        }
    ],
    "hashType": "sha256"
}